LICENSE
MANIFEST.in
README.md
requirements.txt
setup.cfg
setup.py
rumble/__init__.py
rumble/adaptiverun.py
rumble/datatypes.py
rumble/report.py
rumble/rumble.py
rumble/utils.py
rumble.egg-info/PKG-INFO
rumble.egg-info/SOURCES.txt
rumble.egg-info/dependency_links.txt
rumble.egg-info/not-zip-safe
rumble.egg-info/requires.txt
rumble.egg-info/top_level.txt