Metadata-Version: 1.1
Name: rumble
Version: 0.0.8
Summary: A library for easily comparing function runtimes.
Home-page: https://github.com/mambocab/rumble
Author: Jim Witschey
Author-email: jim.witschey@gmail.com
License: MIT
Keywords: rumble,timeit,runtime
Platform: UNKNOWN
Classifier: Development Status :: 2 - Pre-Alpha
Classifier: Intended Audience :: Developers
Classifier: License :: OSI Approved :: MIT License
Classifier: Natural Language :: English
Classifier: Programming Language :: Python :: 2
Classifier: Programming Language :: Python :: 2.6
Classifier: Programming Language :: Python :: 2.7
Classifier: Programming Language :: Python :: 3
Classifier: Programming Language :: Python :: 3.3
Classifier: Programming Language :: Python :: 3.4
